aimos_ui/VERSION
aimos_ui/__init__.py
aimos_ui/build/aim_ui_core.py
aimos_ui/build/asset-manifest.json
aimos_ui/build/favicon.ico
aimos_ui/build/index-template.html
aimos_ui/build/index.html
aimos_ui/build/index.html.gz
aimos_ui/build/manifest.json
aimos_ui/build/robots.txt
aimos_ui/build/assets/icomoon/icomoonIcons.css
aimos_ui/build/assets/icomoon/icomoonIcons.css.gz
aimos_ui/build/assets/icomoon/selection.json
aimos_ui/build/assets/icomoon/fonts/icomoon.eot
aimos_ui/build/assets/icomoon/fonts/icomoon.svg
aimos_ui/build/assets/icomoon/fonts/icomoon.ttf
aimos_ui/build/assets/icomoon/fonts/icomoon.woff
aimos_ui/build/assets/inconsolata/inconsolata.css
aimos_ui/build/assets/inconsolata/inconsolata.css.gz
aimos_ui/build/assets/inconsolata/fonts/Inconsolata.ttf
aimos_ui/build/assets/inter/inter.css
aimos_ui/build/assets/inter/inter.css.gz
aimos_ui/build/assets/inter/fonts/Inter.ttf
aimos_ui/build/static/css/9628.f0a21101.chunk.css
aimos_ui/build/static/css/9628.f0a21101.chunk.css.gz
aimos_ui/build/static/css/9628.f0a21101.chunk.css.map
aimos_ui/build/static/css/App.11696a45.chunk.css
aimos_ui/build/static/css/App.11696a45.chunk.css.gz
aimos_ui/build/static/css/App.11696a45.chunk.css.map
aimos_ui/build/static/css/Apps.b0ad9aab.chunk.css
aimos_ui/build/static/css/Apps.b0ad9aab.chunk.css.gz
aimos_ui/build/static/css/Apps.b0ad9aab.chunk.css.map
aimos_ui/build/static/css/Explorer.68d25825.chunk.css
aimos_ui/build/static/css/Explorer.68d25825.chunk.css.gz
aimos_ui/build/static/css/Explorer.68d25825.chunk.css.map
aimos_ui/build/static/css/Explorers.f0c0b4d4.chunk.css
aimos_ui/build/static/css/Explorers.f0c0b4d4.chunk.css.gz
aimos_ui/build/static/css/Explorers.f0c0b4d4.chunk.css.map
aimos_ui/build/static/css/LineChart.bca6567e.chunk.css
aimos_ui/build/static/css/LineChart.bca6567e.chunk.css.gz
aimos_ui/build/static/css/LineChart.bca6567e.chunk.css.map
aimos_ui/build/static/css/MetricsExplorer.45ad3bc4.chunk.css
aimos_ui/build/static/css/MetricsExplorer.45ad3bc4.chunk.css.gz
aimos_ui-1.0.0.dist-info/METADATA
aimos_ui-1.0.0.dist-info/WHEEL
aimos_ui-1.0.0.dist-info/top_level.txt
aimos_ui-1.0.0.dist-info/RECORD
