Metadata-Version: 2.1
Name: aimos-ui
Version: 1.0.0
Summary: AimOS UI
Home-page: UNKNOWN
License: UNKNOWN
Platform: UNKNOWN
